eldian/__init__.py
eldian/core/__init__.py
eldian/core/dicts.py
eldian/core/mapper.py
eldian/core/types.py
eldian/partials.py
eldian/util.py
eldian/validation/__init__.py
eldian/validation/types.py
eldian-0.1.0.dist-info/LICENSE
eldian-0.1.0.dist-info/WHEEL
eldian-0.1.0.dist-info/METADATA
eldian-0.1.0.dist-info/RECORD
